LICENSE
MANIFEST.in
README.md
pyproject.toml
setup.cfg
setup.py
docs/build/man/moonspec.1
docs/build/text/index.txt
docs/build/text/quickstart.txt
docs/build/text/apidoc/moonspec.api.interface.txt
docs/build/text/apidoc/moonspec.api.txt
moonspec/__init__.py
moonspec/main.py
moonspec/output.py
moonspec/runner.py
moonspec/state.py
moonspec/utils.py
moonspec.egg-info/PKG-INFO
moonspec.egg-info/SOURCES.txt
moonspec.egg-info/dependency_links.txt
moonspec.egg-info/entry_points.txt
moonspec.egg-info/requires.txt
moonspec.egg-info/top_level.txt
moonspec/api/__init__.py
moonspec/api/_utils.py
moonspec/api/fact.py
moonspec/api/subject.py
moonspec/api/interface/__init__.py
moonspec/api/interface/facter.py
moonspec/api/interface/fs.py
moonspec/api/interface/host.py
moonspec/api/interface/inet.py
moonspec/api/interface/libvirtd.py
moonspec/api/interface/osqueryd.py
moonspec/api/interface/ssl.py
moonspec/api/interface/systemd.py