Metadata-Version: 2.1
Name: moonspec
Version: 0.1.7
Summary: Infrastructure test framework
Home-page: https://github.com/moonspec/moonspec
Author: Matiss Treinis
Author-email: matiss@hub256.com
License: Apache 2.0
Download-URL: https://github.com/moonspec/moonspec
Platform: UNIX
Classifier: Development Status :: 4 - Beta
Classifier: Environment :: Console
Classifier: Intended Audience :: System Administrators
Classifier: License :: OSI Approved :: Apache Software License
Classifier: Operating System :: POSIX :: Linux
Classifier: Operating System :: POSIX
Classifier: Operating System :: Unix
Classifier: Programming Language :: Python :: 3 :: Only
Classifier: Topic :: System :: Monitoring
Classifier: Topic :: System :: Networking :: Monitoring
Classifier: Topic :: Utilities
Classifier: Topic :: System :: Systems Administration
Provides-Extra: systemd_logging
Provides-Extra: osquery_support
Provides-Extra: libvirt_support
